service_linker/__init__.py
service_linker/adapter.py
service_linker/core.py
service_linker/adapters/__init__.py
service_linker/adapters/elasticsearch_adapter.py
service_linker/adapters/kafka_consumer_adapter.py
service_linker/adapters/kafka_producer_adapter.py
service_linker/adapters/mongo_adapter.py
service_linker/adapters/mysql_raw_adapter.py
service_linker/adapters/redis_adapter.py
service_linker-0.0.2a0.dist-info/LICENSE
service_linker-0.0.2a0.dist-info/METADATA
service_linker-0.0.2a0.dist-info/WHEEL
service_linker-0.0.2a0.dist-info/top_level.txt
service_linker-0.0.2a0.dist-info/RECORD
