Metadata-Version: 2.2
Name: service_linker
Version: 0.0.2a0
Summary: A simple Python library to manage kinds of services connections
Author-email: zjd-melo <zhujiadong.melo@gmail.com>
License: MIT License
Project-URL: Homepage, https://github.com/zjd-melo/service_linker
Project-URL: Repository, https://github.com/zjd-melo/service_linker.git
Project-URL: Issues, https://github.com/zjd-melo/service_linker/issues
Keywords: services manage
Classifier: Programming Language :: Python :: 3
Classifier: License :: OSI Approved :: MIT License
Classifier: Operating System :: OS Independent
License-File: LICENSE
